flask_mysqldb/VERSION
flask_mysqldb/__init__.py
Flask_MySQLdb-2.0.0.dist-info/AUTHORS
Flask_MySQLdb-2.0.0.dist-info/LICENSE
Flask_MySQLdb-2.0.0.dist-info/METADATA
Flask_MySQLdb-2.0.0.dist-info/WHEEL
Flask_MySQLdb-2.0.0.dist-info/top_level.txt
Flask_MySQLdb-2.0.0.dist-info/RECORD
