Metadata-Version: 2.1
Name: Flask-MySQLdb
Version: 2.0.0
Summary: MySQLdb extension for Flask
Home-page: https://github.com/alexferl/flask-mysqldb
Author: Alexandre Ferland
Author-email: me@alexferl.com
License: MIT
Classifier: Environment :: Web Environment
Classifier: Intended Audience :: Developers
Classifier: License :: OSI Approved :: MIT License
Classifier: Operating System :: OS Independent
Classifier: Programming Language :: Python :: 3.8
Classifier: Programming Language :: Python :: 3.9
Classifier: Programming Language :: Python :: 3.10
Classifier: Programming Language :: Python :: 3.11
Classifier: Topic :: Software Development :: Libraries :: Python Modules
Requires-Python: >=3.8
License-File: LICENSE
License-File: AUTHORS
Requires-Dist: Flask>=1.0.4
Requires-Dist: mysqlclient>=2.2.0
